mcp_server_vefaas_browser_use/__init__.py
mcp_server_vefaas_browser_use/server.py
vefaas_browser_use_mcp_server-0.1.0.dist-info/METADATA
vefaas_browser_use_mcp_server-0.1.0.dist-info/WHEEL
vefaas_browser_use_mcp_server-0.1.0.dist-info/entry_points.txt
vefaas_browser_use_mcp_server-0.1.0.dist-info/top_level.txt
vefaas_browser_use_mcp_server-0.1.0.dist-info/RECORD
