Metadata-Version: 2.4
Name: vefaas-browser-use-mcp-server
Version: 0.1.0
Summary: MCP server for automating browser operations
Requires-Python: >=3.13
Requires-Dist: mcp==1.3.0
Requires-Dist: requests==2.32.3
